modular_cli_sdk/__init__.py
modular_cli_sdk/client/__init__.py
modular_cli_sdk/client/ssm_client.py
modular_cli_sdk/commons/__init__.py
modular_cli_sdk/commons/constants.py
modular_cli_sdk/commons/exception.py
modular_cli_sdk/commons/logger.py
modular_cli_sdk/services/__init__.py
modular_cli_sdk/services/credentials_manager.py
modular_cli_sdk/utils/__init__.py
modular_cli_sdk/utils/view_utils.py
modular_cli_sdk-3.1.2.dist-info/licenses/LICENSE
modular_cli_sdk-3.1.2.dist-info/METADATA
modular_cli_sdk-3.1.2.dist-info/WHEEL
modular_cli_sdk-3.1.2.dist-info/top_level.txt
modular_cli_sdk-3.1.2.dist-info/RECORD
