Metadata-Version: 2.4
Name: modular-cli-sdk
Version: 3.1.2
Summary: Core component for CLI tools built atop of Modular Framework
Author-email: EPAM Systems <support@syndicate.team>
License:                                  Apache License
Project-URL: Homepage, https://github.com/epam/modular-cli-sdk
Project-URL: Documentation, https://github.com/epam/modular-cli-sdk/blob/main/README.md
Project-URL: Changelog, https://github.com/epam/modular-cli-sdk/blob/main/CHANGELOG.md
Classifier: Programming Language :: Python :: 3
Classifier: License :: OSI Approved :: Apache Software License
Classifier: Operating System :: OS Independent
Requires-Python: >=3.10
License-File: LICENSE
Requires-Dist: boto3<2,>=1.36.11
Requires-Dist: botocore<2,>=1.36.11
Requires-Dist: click<9.0.0,>=8.0.0
Provides-Extra: hvac
Requires-Dist: hvac~=2.1.0; extra == "hvac"
Dynamic: license-file
